{
  "version": "1.0",
  "timestamp": "2026-07-23T06:59:24.179Z",
  "context": "phase",
  "phase": "05",
  "phase_name": "hardening-portability",
  "phase_dir": ".planning/phases/05-hardening-portability",
  "activity": "Code review and auto-fix cycle completed; paused before final verification re-review due to context limit.",
  "status": "paused",
  "remaining_tasks": [
    {"id": 1, "name": "Run scoped re-review of files touched by fix commits to verify fixes", "route": "/gsd-code-review 5 --files=Public/Set-AdmanUserPassword.ps1,Public/New-AdmanUser.ps1,Public/Set-AdmanLocalUser.ps1,Private/Workflow/Get-AdmanOffboardingState.ps1,Public/Start-AdmanUserOnboarding.ps1,Public/Config/Export-AdmanConfig.ps1,tests/Workflow.OffboardingState.Tests.ps1,Public/Start-Adman.ps1,build/Sign-AdmanModule.ps1,.github/workflows/ci.yml,Private/Config/Initialize-AdmanConfig.ps1"},
    {"id": 2, "name": "Address any remaining review findings from verification re-review", "route": "/gsd-code-review 5 --fix or manual edits"},
    {"id": 3, "name": "Run phase verification and produce/update 05-VERIFICATION.md", "route": "/gsd-verify-work 05 or /gsd-execute-phase 05"},
    {"id": 4, "name": "Commit any remaining uncommitted work and finalize phase state", "route": "/gsd-quick or manual git"}
  ],
  "blockers": [
    {"description": "Conversation context at 78% — a full 56-file re-review would risk truncation.", "type": "technical", "workaround": "Use --files scoped to the 11 files changed by fix commits, or --depth=quick."}
  ],
  "human_actions_pending": [],
  "decisions": [
    {"decision": "Applied 11 of 12 critical/warning findings from the second review pass.", "rationale": "Fixer agent committed each fix atomically; WR-08 was skipped because the source already pinned -Server.", "phase": "05"},
    {"decision": "Paused instead of running the third /gsd-code-review 5 invocation.", "rationale": "Context warning at 78% made a full review unsafe; user chose to checkpoint.", "phase": "05"}
  ],
  "uncommitted_files": [
    ".planning/STATE.md",
    ".planning/config.json",
    ".planning/phases/05-hardening-portability/05-01b-PLAN.md",
    ".planning/phases/05-hardening-portability/05-04-PLAN.md",
    "Public/New-AdmanLocalUser.ps1",
    "tests/TestResults.xml",
    "tests/coverage.xml"
  ],
  "next_action": "Run scoped re-review of the files touched by the 11 fix commits to verify the fixes.",
  "context_notes": "We have completed a full review/fix cycle on Phase 5. The 05-REVIEW-FIX.md report documents 11 fixed and 1 skipped finding. A final re-review is needed to confirm the fixes, but context is too low for the original 56-file scope. Resume with a targeted re-review of only the files that changed during the fix pass."
}
